{
    "textures": {
        "background": {
            "file":  "textures/ice.png",
            "wrapS": "repeat",
            "wrapT": "repeat"
        },
        "square":{
            "file": "textures/square.png"
        },
        "square-selected":{
            "file": "textures/square_selected.png"
        },
        "square-swap":{
            "file": "textures/square_swap.png"
        },
        "square-attacked":{
            "file": "textures/square_attacked.png"
        },
        "transparent":{
            "file": "textures/transparent_texture.png"
        },
        "basic-red":{
            "file": "textures/red_unit.png"
        },
        "basic-blue":{
            "file": "textures/blue_unit.png"
        },
        "basic-green":{
            "file": "textures/green_unit.png"
        },
        "diagonal-blue":{
            "file": "textures/diagonal_blue.png"
        },
        "diagonal-green":{
            "file": "textures/diagonal_green.png"
        },
        "diagonal-red":{
            "file": "textures/diagonal_red.png"
        },
        "three-way-blue":{
            "file": "textures/three_way_blue_unit.png"
        },
        "three-way-green":{
            "file": "textures/three_way_green_unit.png"
        },
        "three-way-red":{
            "file": "textures/three_way_red_unit.png"
        },
        "two-forward-blue":{
            "file": "textures/two_forward_blue_unit.png"
        },
        "two-forward-green":{
            "file": "textures/two_forward_green_unit.png"
        },
        "two-forward-red":{
            "file": "textures/two_forward_red_unit.png"
        },
        "button": {
            "file":  "textures/button.png"
        }
    },
    "fonts": {
        "pixel32": {
            "file":     "fonts/LightPixel7.ttf",
            "size":     32
        }
    },
    "sounds" : {
        "fusion" : {
            "type": "sample",
            "file": "sounds/fusion.ogg"
        },
        "laser" : {
            "type": "sample",
            "file": "sounds/laser.ogg",
            "volume": 0.5
        },
        "blast" : {
            "type": "sample",
            "file": "sounds/explode.ogg"
        },
        "bang" : {
            "type": "sample",
            "file": "sounds/bang.ogg",
            "volume": 0.8
        }
    },
    "widgets": {
        "textbutton" : "widgets/textbutton.json"
    },
    "jsons" : {
        "constants" : "json/constants.json",
        "boardMember" : "json/boardMember.json",
        "board" : "json/board.json"
    },
    "scene2s" : {
        "menu": {
            "type"      : "Node",
            "format"    : {
                "type"        : "Float",
                "orientation" : "vertical",
                "x_alignment" : "center",
                "y_alignment" : "middle"
            },
            "children":  {
               "host": {
                    "type"   : "Widget",
                    "data"   : {
                        "key"     : "textbutton",
                        "variables" : {
                            "size": [400,100],
                            "text": "Play Game",
                            "color": "#000088"
                        }
                    },
                    "layout" : {
                        "priority" : 1,
                        "padding"  : [0,50,0,0]
                    }
                },
               "join": {
                    "type"   : "Widget",
                    "data"   : {
                        "key"     : "textbutton",
                        "variables" : {
                            "size": [400,100],
                            "text": "Level Editor",
                            "color": "#000088"
                        }
                    },
                    "layout" : {
                        "priority" : 1,
                        "padding"  : [0,0,0,0]
                    }
                }
            }
        }
    }
}
